{
  "cli_args": [
    "--max-num-iterations=30000",

    "--pipeline.model.rasterize_mode=antialiased",
    "--pipeline.model.num_downscales=0",
    "--pipeline.model.resolution_schedule=1000",
    "--pipeline.model.refine_every=50",

    "--pipeline.model.use_scale_regularization=True",

    "--pipeline.model.sh_degree=4",
    "--pipeline.model.sh_degree_interval=500",

    "--pipeline.model.cull_alpha_thresh=0.005",
    "--pipeline.model.stop_split_at=25000",
    "--pipeline.model.densify_grad_thresh=0.0005",

    "--pipeline.model.camera_optimizer.mode=SO3xR3",
    "--pipeline.model.use_bilateral_grid=True",

    "--pipeline.datamanager.cache_images_type=float32"
  ],
  "data_args": [
    "--eval-mode=all"
  ],
  "export_splat": {
    "enabled": false,
    "ply_color_mode": "sh_coeffs",
    "export_dir": "exports\\splat",
    "timestamp": null
  }
}

